notion_graph/__init__.py
notion_graph/__main__.py
notion_graph/cli.py
notion_graph/helper.py
notion_graph/parser.py
notion_graph-0.3.0.dist-info/WHEEL
notion_graph-0.3.0.dist-info/METADATA
notion_graph-0.3.0.dist-info/licenses/LICENSE
notion_graph-0.3.0.dist-info/RECORD
