Metadata-Version: 2.1
Name: notion-graph
Version: 0.3.0
Summary: Generate a roam research like network graph view from your Notion pages.
License: MIT
Author-email: Steve Sun <sund.chn@gmail.com>
Requires-Python: >=3.9
Requires-Dist: notion-client>=2.0.0
Requires-Dist: pyvis==0.3.1
